mdx_macros
