Metadata-Version: 1.0
Name: markdown-macros
Version: 0.1.2
Summary: An extension for python-markdown that add Trac-like macro support.
Home-page: https://github.com/wnielson/markdown-macros
Author: Weston Nielson
Author-email: wnielson@github
License: MIT
Keywords: markdown macro macros
Platform: UNKNOWN
